wikimapper/__init__.py
wikimapper/__version__.py
wikimapper/cli.py
wikimapper/download.py
wikimapper/mapper.py
wikimapper/processor.py
wikimapper-0.1.5.dist-info/LICENSE
wikimapper-0.1.5.dist-info/METADATA
wikimapper-0.1.5.dist-info/WHEEL
wikimapper-0.1.5.dist-info/entry_points.txt
wikimapper-0.1.5.dist-info/top_level.txt
wikimapper-0.1.5.dist-info/RECORD
