Metadata-Version: 2.1
Name: wikimapper
Version: 0.1.5
Summary: Mapping Wikidata and Wikipedia entities to each other
Home-page: https://github.com/jcklie/wikimapper
Author: Jan-Christoph Klie
Author-email: git@mrklie.com
License: Apache License 2.0
Project-URL: Bug Tracker, https://github.com/jcklie/wikimapper/issues
Project-URL: Documentation, https://github.com/jcklie/wikimapper
Project-URL: Source Code, https://github.com/jcklie/wikimapper
Keywords: wikidata wikipedia wiki kb knowledge-base
Platform: UNKNOWN
Classifier: Development Status :: 4 - Beta
Classifier: Intended Audience :: Developers
Classifier: Intended Audience :: Science/Research
Classifier: License :: OSI Approved :: Apache Software License
Classifier: Programming Language :: Python :: 3 :: Only
Classifier: Programming Language :: Python :: 3.5
Classifier: Programming Language :: Python :: 3.6
Classifier: Programming Language :: Python :: 3.7
Classifier: Topic :: Internet :: WWW/HTTP :: Dynamic Content :: Wiki
Classifier: Topic :: Software Development :: Libraries
Classifier: Topic :: Scientific/Engineering :: Human Machine Interfaces
Classifier: Topic :: Scientific/Engineering :: Information Analysis
Classifier: Topic :: Text Processing :: Linguistic
Requires-Python: >=3.5.0
Provides-Extra: dev
Requires-Dist: black ; extra == 'dev'
Requires-Dist: twine ; extra == 'dev'
Requires-Dist: pygments ; extra == 'dev'
Requires-Dist: wheel ; extra == 'dev'
Provides-Extra: doc
Provides-Extra: test
Requires-Dist: tox ; extra == 'test'
Requires-Dist: pytest ; extra == 'test'
Requires-Dist: codecov ; extra == 'test'
Requires-Dist: pytest-cov ; extra == 'test'
